IsingSDGC/__init__.py
IsingSDGC/modulo.py
IsingSDGC-0.2.0.dist-info/METADATA
IsingSDGC-0.2.0.dist-info/WHEEL
IsingSDGC-0.2.0.dist-info/top_level.txt
IsingSDGC-0.2.0.dist-info/RECORD
