Metadata-Version: 2.1
Name: IsingSDGC
Version: 0.2.0
Summary: IsingSDGC
Home-page: https://gitlab.com/sebasdgc14/personal
Author: Sebastian Diaz Granados Cano
Author-email: sebasdgc14@gmail.com
License: MIT
Requires-Python: >=3.10.12
Requires-Dist: matplotlib ==3.8.1
Requires-Dist: numpy ==1.26.1
